slyp/__init__.py
slyp/__main__.py
slyp/cli.py
slyp/codes.py
slyp/driver.py
slyp/file_cache.py
slyp/hashable_file.py
slyp/result.py
slyp/checkers/__init__.py
slyp/checkers/abstract/__init__.py
slyp/checkers/abstract/_base.py
slyp/checkers/abstract/matching_branches.py
slyp/checkers/concrete/__init__.py
slyp/checkers/concrete/_base.py
slyp/checkers/concrete/str_concat.py
slyp/fixer/__init__.py
slyp/fixer/transformer.py
slyp-0.8.2.dist-info/LICENSE.txt
slyp-0.8.2.dist-info/METADATA
slyp-0.8.2.dist-info/WHEEL
slyp-0.8.2.dist-info/entry_points.txt
slyp-0.8.2.dist-info/top_level.txt
slyp-0.8.2.dist-info/RECORD
