Metadata-Version: 2.2
Name: slyp
Version: 0.8.2
Summary: Stephen Lints Your Python
Author-email: Stephen Rosen <sirosen@globus.org>
License: MIT
Project-URL: source, https://github.com/sirosen/slyp
Classifier: Development Status :: 3 - Alpha
Classifier: Programming Language :: Python
Classifier: Programming Language :: Python :: 3.8
Classifier: Programming Language :: Python :: 3.9
Classifier: Programming Language :: Python :: 3.10
Classifier: Programming Language :: Python :: 3.11
Classifier: Programming Language :: Python :: 3.12
Requires-Python: >=3.8
License-File: LICENSE.txt
Requires-Dist: libcst>=1
Requires-Dist: typing_extensions>=4.0; python_version < "3.10"
